xpuz
