Metadata-Version: 2.1
Name: xpuz
Version: 2.2.106
Summary: Design and play procedurally generated crosswords
Author: Tomas Vana
License: MIT
Project-URL: Homepage, https://github.com/tomasvana10/xpuz
Keywords: crosswords,procedural generation,games
Classifier: Topic :: Multimedia
Classifier: Development Status :: 5 - Production/Stable
Classifier: Intended Audience :: End Users/Desktop
Classifier: Intended Audience :: Developers
Classifier: Intended Audience :: Education
Classifier: License :: OSI Approved :: MIT License
Classifier: Operating System :: OS Independent
Classifier: Programming Language :: Python
Classifier: Programming Language :: Python :: 3
Classifier: Programming Language :: JavaScript
Classifier: Topic :: Text Processing :: Markup :: HTML
Classifier: Framework :: Flask
Classifier: Topic :: Software Development :: Localization
Classifier: Topic :: Education
Classifier: Topic :: Games/Entertainment
License-File: LICENSE.md
Requires-Dist: Babel
Requires-Dist: customtkinter
Requires-Dist: Flask
Requires-Dist: flask-babel
Requires-Dist: Pillow
Requires-Dist: regex
Requires-Dist: platformdirs
Requires-Dist: pathvalidate
Requires-Dist: CTkToolTip
Requires-Dist: pywebview
Provides-Extra: pdf
Requires-Dist: pycairo ; extra == 'pdf'
